[
  {
    "nama": "Sukarno",
    "nama2": "Ir. Sukarno",
    "kategori": "Proklamator",
    "asal": "Blitar",
    "lahir": "6 Juni 1901",
    "usia": "69",
    "gugur": "21 Juni 1970",
    "lokasimakam": "Blitar, Jawa Timur",
    "history": "Sukarno adalah Presiden pertama Republik Indonesia dan salah satu tokoh Proklamasi Kemerdekaan Indonesia.",
    "img": "https://example.com/images/sukarno.jpg"
  },
  {
    "nama": "Mohammad Hatta",
    "nama2": "Drs. Mohammad Hatta",
    "kategori": "Proklamator",
    "asal": "Bukittinggi",
    "lahir": "12 Agustus 1902",
    "usia": "77",
    "gugur": "14 Maret 1980",
    "lokasimakam": "Jakarta",
    "history": "Mohammad Hatta adalah Wakil Presiden pertama Republik Indonesia dan salah satu tokoh Proklamasi Kemerdekaan Indonesia.",
    "img": "https://example.com/images/hatta.jpg"
  },
  {
    "nama": "R.A. Kartini",
    "nama2": "Raden Adjeng Kartini",
    "kategori": "Pahlawan Emansipasi Wanita",
    "asal": "Jepara",
    "lahir": "21 April 1879",
    "usia": "25",
    "gugur": "17 September 1904",
    "lokasimakam": "Rembang, Jawa Tengah",
    "history": "Kartini adalah tokoh pelopor emansipasi wanita di Indonesia.",
    "img": "https://example.com/images/kartini.jpg"
  },
  {
    "nama": "Diponegoro",
    "nama2": "Pangeran Diponegoro",
    "kategori": "Pahlawan Nasional",
    "asal": "Yogyakarta",
    "lahir": "11 November 1785",
    "usia": "69",
    "gugur": "8 Januari 1855",
    "lokasimakam": "Makassar, Sulawesi Selatan",
    "history": "Pangeran Diponegoro adalah seorang pahlawan yang memimpin Perang Jawa melawan Belanda pada tahun 1825-1830.",
    "img": "https://example.com/images/diponegoro.jpg"
  },
  {
    "nama": "Cut Nyak Dhien",
    "nama2": "Cut Nyak Dhien",
    "kategori": "Pahlawan Nasional",
    "asal": "Aceh",
    "lahir": "1848",
    "usia": "60",
    "gugur": "6 November 1908",
    "lokasimakam": "Sumedang, Jawa Barat",
    "history": "Cut Nyak Dhien adalah seorang pejuang wanita yang memimpin perlawanan rakyat Aceh melawan penjajahan Belanda.",
    "img": "https://example.com/images/cutnyakdhien.jpg"
  }
]
